tarjimonlib/__init__.py
tarjimonlib-0.0.1.dist-info/METADATA
tarjimonlib-0.0.1.dist-info/WHEEL
tarjimonlib-0.0.1.dist-info/top_level.txt
tarjimonlib-0.0.1.dist-info/RECORD
