Metadata-Version: 2.1
Name: tarjimonlib
Version: 0.0.1
Summary: Ushbu kutubxona tarjima qilish uchun ishlatiladi
Author: Olimov Behruz
Author-email: olimovbehruz738@gmail.com
